plotrisk_python_client/__init__.py
plotrisk_python_client/api_client.py
plotrisk_python_client/configuration.py
plotrisk_python_client/rest.py
plotrisk_python_client/api/__init__.py
plotrisk_python_client/api/keycloak_api.py
plotrisk_python_client/api/plot_risk_resource_api.py
plotrisk_python_client/models/__init__.py
plotrisk_python_client/models/add_plan_filter_and_bulk_select_dto.py
plotrisk_python_client/models/address_dto.py
plotrisk_python_client/models/area.py
plotrisk_python_client/models/area_audit_dto.py
plotrisk_python_client/models/asset_concise_dto.py
plotrisk_python_client/models/asset_dto.py
plotrisk_python_client/models/assets_farmer_filter_dto.py
plotrisk_python_client/models/available_assets_dto.py
plotrisk_python_client/models/available_farmer_dto.py
plotrisk_python_client/models/batch_details_dto.py
plotrisk_python_client/models/batch_details_report_dto.py
plotrisk_python_client/models/batch_details_report_response.py
plotrisk_python_client/models/batch_number_counter.py
plotrisk_python_client/models/batch_report_dto.py
plotrisk_python_client/models/batch_report_search_dto.py
plotrisk_python_client/models/batch_reports_dto.py
plotrisk_python_client/models/batch_sample_dto.py
plotrisk_python_client/models/boundary_metrics.py
plotrisk_python_client/models/bulk_ca_dto.py
plotrisk_python_client/models/bulk_crop_variety_dto.py
plotrisk_python_client/models/bulk_croppable_area_dto.py
plotrisk_python_client/models/bulk_croppable_unit_dto.py
plotrisk_python_client/models/bulk_plan_dto.py
plotrisk_python_client/models/bulk_process_dto.py
plotrisk_python_client/models/bulk_upload_es_dto.py
plotrisk_python_client/models/bulk_upload_task_dto.py
plotrisk_python_client/models/ca_concise_dto.py
plotrisk_python_client/models/ca_dto_for_form.py
plotrisk_python_client/models/ca_status_count_dto.py
plotrisk_python_client/models/ca_user_update_dto.py
plotrisk_python_client/models/chemical_details_dto.py
plotrisk_python_client/models/chemical_type_dto.py
plotrisk_sfplus_internal_client-0.1.0.dist-info/METADATA
plotrisk_sfplus_internal_client-0.1.0.dist-info/WHEEL
plotrisk_sfplus_internal_client-0.1.0.dist-info/top_level.txt
plotrisk_sfplus_internal_client-0.1.0.dist-info/RECORD
