Metadata-Version: 2.1
Name: plotrisk-sfplus-internal-client
Version: 0.1.0
Summary: farm API
Home-page: 
Author-email: 
Keywords: Swagger,farm API
Requires-Dist: urllib3 (>=1.15)
Requires-Dist: six (>=1.10)
Requires-Dist: certifi
Requires-Dist: python-dateutil
